gerel/__init__.py
gerel/algorithms/__init__.py
gerel/algorithms/NEAT/__init__.py
gerel/algorithms/NEAT/functions.py
gerel/algorithms/NEAT/metric.py
gerel/algorithms/NEAT/mutator.py
gerel/algorithms/NEAT/population.py
gerel/algorithms/RES/__init__.py
gerel/algorithms/RES/mutator.py
gerel/algorithms/RES/population.py
gerel/algorithms/SIMPLE/__init__.py
gerel/algorithms/SIMPLE/mutator.py
gerel/algorithms/SIMPLE/population.py
gerel/debug/__init__.py
gerel/debug/class_debug_decorator.py
gerel/debug/genome_validator.py
gerel/debug/model_validator.py
gerel/debug/population_validator.py
gerel/genome/__init__.py
gerel/genome/edge.py
gerel/genome/factories.py
gerel/genome/genome.py
gerel/genome/node.py
gerel/model/__init__.py
gerel/model/model.py
gerel/mutators/__init__.py
gerel/mutators/mutator.py
gerel/populations/__init__.py
gerel/populations/genome_seeders.py
gerel/populations/population.py
gerel/util/__init__.py
gerel/util/activations.py
gerel/util/batch.py
gerel/util/datastore.py
gerel/util/math.py
gerel/util/util.py
gerel-0.0.6.dist-info/LICENSE
gerel-0.0.6.dist-info/METADATA
gerel-0.0.6.dist-info/WHEEL
gerel-0.0.6.dist-info/top_level.txt
gerel-0.0.6.dist-info/RECORD
