Metadata-Version: 2.1
Name: gerel
Version: 0.0.6
Summary: Simple genetic algorithms library for reinforcement learning.
Home-page: https://github.com/mauicv/gerel
Author: mauicv
Author-email: a.thornysort@gmail.com
License: UNKNOWN
Project-URL: Bug Tracker, https://github.com/mauicv/gerel/issues
Platform: UNKNOWN
Classifier: Programming Language :: Python :: 3
Classifier: License :: OSI Approved :: MIT License
Classifier: Operating System :: OS Independent
Requires-Python: >=3.6
License-File: LICENSE
